htmpl/__init__.py
htmpl/assets.py
htmpl/components.py
htmpl/core.py
htmpl/elements.py
htmpl/fastapi.py
htmpl/forms.py
htmpl/htmx.py
htmpl/py.typed
htmpl-0.3.0.dist-info/METADATA
htmpl-0.3.0.dist-info/WHEEL
htmpl-0.3.0.dist-info/RECORD
