Metadata-Version: 2.4
Name: htmpl
Version: 0.3.0
Summary: Type-safe HTML templating with Python 3.14 t-strings
Project-URL: Homepage, https://github.com/julython/htmpl
Project-URL: Documentation, https://github.com/julython/htmpl#readme
Project-URL: Repository, https://github.com/julython/htmpl
Author-email: Robert Myers <robert@julython.org>
License-Expression: MIT
Keywords: fastapi,html,htmx,pico,t-strings,templating
Classifier: Development Status :: 3 - Alpha
Classifier: Framework :: FastAPI
Classifier: Intended Audience :: Developers
Classifier: License :: OSI Approved :: MIT License
Classifier: Programming Language :: Python :: 3.14
Classifier: Topic :: Internet :: WWW/HTTP :: Dynamic Content
Classifier: Topic :: Text Processing :: Markup :: HTML
Classifier: Typing :: Typed
Requires-Python: >=3.14
Provides-Extra: all
Requires-Dist: fastapi>=0.115; extra == 'all'
Requires-Dist: pydantic>=2.0; extra == 'all'
Provides-Extra: dev
Requires-Dist: fastapi>=0.115; extra == 'dev'
Requires-Dist: httpx>=0.28; extra == 'dev'
Requires-Dist: mypy>=1.13; extra == 'dev'
Requires-Dist: pydantic>=2.0; extra == 'dev'
Requires-Dist: pydantic[email]>=2.0; extra == 'dev'
Requires-Dist: pytest-asyncio>=0.24; extra == 'dev'
Requires-Dist: pytest>=8.0; extra == 'dev'
Requires-Dist: ruff>=0.8; extra == 'dev'
Requires-Dist: uvicorn>=0.32; extra == 'dev'
